simpleragharshit/__init__.py
simpleragharshit/config.py
simpleragharshit/embedding.py
simpleragharshit/generator.py
simpleragharshit/indexing.py
simpleragharshit/loader.py
simpleragharshit/pipeline.py
simpleragharshit/retriever.py
simpleragharshit-0.1.1.dist-info/entry_points.txt
simpleragharshit-0.1.1.dist-info/LICENSE
simpleragharshit-0.1.1.dist-info/METADATA
simpleragharshit-0.1.1.dist-info/WHEEL
simpleragharshit-0.1.1.dist-info/RECORD
